aolog/__init__.py
aolog/aolog.py
aolog-0.1.3.dist-info/licenses/LICENSE
aolog-0.1.3.dist-info/METADATA
aolog-0.1.3.dist-info/WHEEL
aolog-0.1.3.dist-info/top_level.txt
aolog-0.1.3.dist-info/RECORD
