Metadata-Version: 2.4
Name: aolog
Version: 0.1.3
Summary: minimal logging class
Author-email: Michael Mahoney <michael.mahoney@alphaomega.com.co>
License: The MIT License (MIT)
License-File: LICENSE
Dynamic: license-file
